{
  "$schema": "https://developer.microsoft.com/json-schemas/fabric/item/report/definition/visualContainer/2.9.0/schema.json",
  "name": "28d39d431b40ab0b9c01",
  "position": {
    "x": 25.040276179516685,
    "y": 160.55235903337169,
    "z": 0,
    "height": 525,
    "width": 1230,
    "tabOrder": 0
  },
  "visual": {
    "visualType": "columnChart",
    "query": {
      "queryState": {
        "Category": {
          "projections": [
            {
              "field": {
                "Column": {
                  "Expression": {
                    "SourceRef": {
                      "Entity": "Grades"
                    }
                  },
                  "Property": "DRENAET"
                }
              },
              "queryRef": "Grades.DRENAET",
              "nativeQueryRef": "DRENAET",
              "active": true
            }
          ]
        },
        "Y": {
          "projections": [
            {
              "field": {
                "Measure": {
                  "Expression": {
                    "SourceRef": {
                      "Entity": "Mesures"
                    }
                  },
                  "Property": "% Of Students With Low Litteracy At EL"
                }
              },
              "queryRef": "Mesures.% Of Students With Low Litteracy At EL",
              "nativeQueryRef": "Endline",
              "displayName": "Endline"
            },
            {
              "field": {
                "Measure": {
                  "Expression": {
                    "SourceRef": {
                      "Entity": "Mesures"
                    }
                  },
                  "Property": "pp Of Litteracy Difficulty Reduction From BL to EL"
                }
              },
              "queryRef": "Mesures.pp Of Litteracy Difficulty Reduction From BL to EL",
              "nativeQueryRef": "Decrease from baseline",
              "displayName": "Decrease from baseline"
            }
          ]
        }
      },
      "sortDefinition": {
        "sort": [
          {
            "field": {
              "Measure": {
                "Expression": {
                  "SourceRef": {
                    "Entity": "Mesures"
                  }
                },
                "Property": "pp Of Litteracy Difficulty Reduction From BL to EL"
              }
            },
            "direction": "Descending"
          }
        ]
      }
    },
    "objects": {
      "legend": [
        {
          "properties": {
            "position": {
              "expr": {
                "Literal": {
                  "Value": "'BottomCenter'"
                }
              }
            }
          }
        }
      ],
      "labels": [
        {
          "properties": {
            "detailLabelPrecision": {
              "expr": {
                "Literal": {
                  "Value": "1L"
                }
              }
            },
            "labelOrientation": {
              "expr": {
                "Literal": {
                  "Value": "1D"
                }
              }
            },
            "labelPosition": {
              "expr": {
                "Literal": {
                  "Value": "'Auto'"
                }
              }
            },
            "optimizeLabelDisplay": {
              "expr": {
                "Literal": {
                  "Value": "true"
                }
              }
            }
          }
        }
      ],
      "valueAxis": [
        {
          "properties": {
            "end": {
              "expr": {
                "Literal": {
                  "Value": "1D"
                }
              }
            },
            "start": {
              "expr": {
                "Literal": {
                  "Value": "0D"
                }
              }
            }
          }
        }
      ],
      "dataPoint": [
        {
          "properties": {
            "fill": {
              "solid": {
                "color": {
                  "expr": {
                    "ThemeDataColor": {
                      "ColorId": 7,
                      "Percent": 0
                    }
                  }
                }
              }
            }
          },
          "selector": {
            "metadata": "Mesures.Percentage Of Students Tested With Low Litteracy In Grade EL"
          }
        },
        {
          "properties": {
            "fill": {
              "solid": {
                "color": {
                  "expr": {
                    "ThemeDataColor": {
                      "ColorId": 3,
                      "Percent": 0
                    }
                  }
                }
              }
            }
          },
          "selector": {
            "metadata": "Mesures.Litteracy Difficulty Reduction BL to EL (PP)"
          }
        },
        {
          "properties": {
            "fill": {
              "solid": {
                "color": {
                  "expr": {
                    "ThemeDataColor": {
                      "ColorId": 7,
                      "Percent": 0
                    }
                  }
                }
              }
            }
          },
          "selector": {
            "metadata": "Mesures.pp Of Litteracy Difficulty Reduction From BL to EL"
          }
        }
      ],
      "zoom": [
        {
          "properties": {
            "show": {
              "expr": {
                "Literal": {
                  "Value": "false"
                }
              }
            }
          }
        }
      ],
      "categoryAxis": [
        {
          "properties": {
            "innerPadding": {
              "expr": {
                "Literal": {
                  "Value": "50L"
                }
              }
            },
            "preferredCategoryWidth": {
              "expr": {
                "Literal": {
                  "Value": "80D"
                }
              }
            }
          }
        }
      ]
    },
    "visualContainerObjects": {
      "title": [
        {
          "properties": {
            "text": {
              "expr": {
                "Literal": {
                  "Value": "'Reduction in the number of learners in Literacy difficulty'"
                }
              }
            },
            "fontSize": {
              "expr": {
                "Literal": {
                  "Value": "14D"
                }
              }
            }
          }
        }
      ],
      "subTitle": [
        {
          "properties": {
            "text": {
              "expr": {
                "Literal": {
                  "Value": "'Decrease of the percentage of students who cannot read words from BL to EL'"
                }
              }
            },
            "fontSize": {
              "expr": {
                "Literal": {
                  "Value": "11D"
                }
              }
            }
          }
        }
      ],
      "stylePreset": [
        {
          "properties": {
            "name": {
              "expr": {
                "Literal": {
                  "Value": "'Data labels'"
                }
              }
            }
          }
        }
      ],
      "divider": [
        {
          "properties": {
            "show": {
              "expr": {
                "Literal": {
                  "Value": "true"
                }
              }
            }
          }
        }
      ],
      "spacing": [
        {
          "properties": {
            "spaceBelowTitle": {
              "expr": {
                "Literal": {
                  "Value": "5D"
                }
              }
            },
            "spaceBelowSubTitle": {
              "expr": {
                "Literal": {
                  "Value": "10D"
                }
              }
            },
            "spaceBelowTitleArea": {
              "expr": {
                "Literal": {
                  "Value": "10D"
                }
              }
            }
          }
        }
      ]
    },
    "drillFilterOtherVisuals": true
  }
}